setup.cfg
setup.py
PyCrawler3.egg-info/SOURCES.txt
pycrawler/__init__.py
pycrawler/crawler.py
pycrawler/http.py
pycrawler/page.py
pycrawler3.egg-info/PKG-INFO
pycrawler3.egg-info/SOURCES.txt
pycrawler3.egg-info/dependency_links.txt
pycrawler3.egg-info/top_level.txt