Metadata-Version: 1.1
Name: PyCrawler3
Version: 1.1.0
Summary: A Python crawler tool to grab page(s) information from html data. This only support Python 3
Home-page: https://github.com/slaveofcode/pycrawler
Author: Aditya Kresna Permana
Author-email: zeandcode@gmail.com
License: UNKNOWN
Download-URL: https://github.com/slaveofcode/pycrawler/archive/v1.1.0.zip
Keywords: crawler,pycrawler,boilerpipe,boilerpipe3,page crawler,html crawler,document crawler
Platform: UNKNOWN
